[{"ShardName": "0", "NodeName": "0S1", "Coordinate": "0", "Peerid": "2dda64689cfa361014b97bb0e76cd2ee753a4015", "Neighbor": [16, 4, 1]}, {"ShardName": "0", "NodeName": "0S2", "Coordinate": "1", "Peerid": "e548516b68adb5fc52d327e360397fb681f634d7", "Neighbor": [17, 5, 2, 0]}, {"ShardName": "1", "NodeName": "1S1", "Coordinate": "0", "Peerid": "26796b2fc867bab60a25b3d62461bc2119f05543", "Neighbor": [16, 4, 1]}, {"ShardName": "1", "NodeName": "1S2", "Coordinate": "1", "Peerid": "91c1c74c303dd7c62e5aa0829da00138f6f08be1", "Neighbor": [17, 5, 2, 0]}]