["\"{\"genesis_time\": \"2020-04-08T10:20:29.240795187Z\", \"chain_id\": \"test-chain-MbjOgv\", \"consensus_params\": {\"block\": {\"max_bytes\": \"22020096\", \"max_gas\": \"-1\", \"time_iota_ms\": \"1000\"}, \"evidence\": {\"max_age\": \"100000\"}, \"validator\": {\"pub_key_types\": [\"ed25519\"]}}, \"validators\": [{\"address\": \"48337414A6C1587F2FA6439456EF87CF24E96A97\", \"pub_key\": {\"type\": \"tendermint/PubKeyEd25519\", \"value\": \"SK+2DmGwKNYiwyBwyL3wl6q/IcfTinsptlIXTbA8hog=\"}, \"power\": \"1000\", \"name\": \"TTANode1\"}, {\"address\": \"75EF9AD2ED897801F94A7AF41E9127D446E2732C\", \"pub_key\": {\"type\": \"tendermint/PubKeyEd25519\", \"value\": \"orTHtRm5STe4BzfVB3ho27d6zfMt6PwaML3PHqUHN44=\"}, \"power\": \"10\", \"name\": \"TTANode2\"}, {\"address\": \"07B11BA6FAAD8DF5C35ED241B2C8036513B4F343\", \"pub_key\": {\"type\": \"tendermint/PubKeyEd25519\", \"value\": \"4XOcKbGr4icB9kylqT/yxjkQZlSGB+V4PB7b9Z5cRpw=\"}, \"power\": \"10\", \"name\": \"TTANode3\"}, {\"address\": \"BB2F3E90EDCF64B748177B54D9E56DE99CCCCCBD\", \"pub_key\": {\"type\": \"tendermint/PubKeyEd25519\", \"value\": \"QCX2Bv8xebe935uIk+Dc4u6yHflCKBVZ1cKj/YYkoVk=\"}, \"power\": \"10\", \"name\": \"TTANode4\"}], \"app_hash\": \"\"}\"", "\"{\"genesis_time\": \"2020-04-08T10:21:00.55271367Z\", \"chain_id\": \"test-chain-hLT4Xg\", \"consensus_params\": {\"block\": {\"max_bytes\": \"22020096\", \"max_gas\": \"-1\", \"time_iota_ms\": \"1000\"}, \"evidence\": {\"max_age\": \"100000\"}, \"validator\": {\"pub_key_types\": [\"ed25519\"]}}, \"validators\": [{\"address\": \"AEC0CCFFD0B654FC8A76BAE91AD4968F79A59DB5\", \"pub_key\": {\"type\": \"tendermint/PubKeyEd25519\", \"value\": \"v39gBYcgT5huBx6M8eRM6RDQnvTGxuXfOfvmdzekcNg=\"}, \"power\": \"1000\", \"name\": \"TTBNode1\"}, {\"address\": \"36B2412466EFDA57EDA2E02851CB263946DE39CA\", \"pub_key\": {\"type\": \"tendermint/PubKeyEd25519\", \"value\": \"VGO+4rTEDuiCuYfOH3g80y7fDAtxoPA/sum++yh0fIE=\"}, \"power\": \"10\", \"name\": \"TTBNode2\"}, {\"address\": \"F4931BD9020179145EA50277AE7CB74482A1B985\", \"pub_key\": {\"type\": \"tendermint/PubKeyEd25519\", \"value\": \"KA+qnX0hD+3HLmjInsUy1xt14+Sz9QegKONpHPZgwvk=\"}, \"power\": \"10\", \"name\": \"TTBNode3\"}, {\"address\": \"D2A541AC7F8E5DE2888D0BDD596AC586EE0F98E1\", \"pub_key\": {\"type\": \"tendermint/PubKeyEd25519\", \"value\": \"ObpYKUIw6fZIPMgXm8SzTYkHaW8Na2ff+VMCUuufynk=\"}, \"power\": \"10\", \"name\": \"TTBNode4\"}], \"app_hash\": \"\"}\""]